test1234567/__init__.py
test1234567/test.py
test1234567-0.14.dist-info/METADATA
test1234567-0.14.dist-info/WHEEL
test1234567-0.14.dist-info/top_level.txt
test1234567-0.14.dist-info/zip-safe
test1234567-0.14.dist-info/RECORD
