Metadata-Version: 2.1
Name: test1234567
Version: 0.14
Summary: test1234567 description
Home-page: UNKNOWN
Author: vitaliyrakitin
Author-email: vitaliyrakitin@ya.ru
License: UNKNOWN
Platform: UNKNOWN
